lnetatmo.py
lnetatmo-4.2.0.dist-info/LICENSE.txt
lnetatmo-4.2.0.dist-info/METADATA
lnetatmo-4.2.0.dist-info/WHEEL
lnetatmo-4.2.0.dist-info/top_level.txt
lnetatmo-4.2.0.dist-info/RECORD
