Metadata-Version: 2.1
Name: lnetatmo
Version: 4.2.0
Summary: Simple API to access Netatmo weather station data from any python script.
Home-page: https://github.com/philippelt/netatmo-api-python
Download-URL: https://github.com/philippelt/netatmo-api-python/archive/v4.2.0.tar.gz
Author: Philippe Larduinat
Author-email: ph.larduinat@wanadoo.fr
License: GPL V3
Classifier: Development Status :: 5 - Production/Stable
Classifier: Intended Audience :: Developers
Classifier: Programming Language :: Python :: 2.7
Classifier: Programming Language :: Python :: 3
License-File: LICENSE.txt
